pylpconcat/__init__.py
pylpconcat/transformer.py
pylpconcat-0.1.1.dist-info/DESCRIPTION.rst
pylpconcat-0.1.1.dist-info/METADATA
pylpconcat-0.1.1.dist-info/RECORD
pylpconcat-0.1.1.dist-info/WHEEL
pylpconcat-0.1.1.dist-info/metadata.json
pylpconcat-0.1.1.dist-info/top_level.txt
